Metadata-Version: 2.1
Name: airtable-async-ti
Version: 0.0.1b11
Summary: Forked asynchronous Python API Wrapper for the Airtable API - return id in responses
Home-page: https://github.com/tangibleintelligence/airbase
Author: Jennifer Trippett
Author-email: lfparis@gmail.com
License: The MIT License (MIT)
Keywords: airtable,api,async,async.io
Platform: UNKNOWN
Classifier: Development Status :: 2 - Pre-Alpha
Classifier: Environment :: Console
Classifier: Framework :: AsyncIO
Classifier: Intended Audience :: Developers
Classifier: Programming Language :: Python
Classifier: Topic :: Software Development
Classifier: Programming Language :: Python :: 3.7
Classifier: Programming Language :: Python :: 3.8
Classifier: Programming Language :: Python :: Implementation :: CPython
Requires-Python: >=3.7
Requires-Dist: aiohttp
Provides-Extra: tools
Requires-Dist: pandas ; extra == 'tools'
